ozmo/__init__.py
ozmo/cli.py
ozmo-1.0.4.dist-info/LICENSE.txt
ozmo-1.0.4.dist-info/METADATA
ozmo-1.0.4.dist-info/WHEEL
ozmo-1.0.4.dist-info/entry_points.txt
ozmo-1.0.4.dist-info/top_level.txt
ozmo-1.0.4.dist-info/RECORD
